ambiance/__init__.py
ambiance/__version__.py
ambiance/_doc.py
ambiance/ambiance.py
ambiance-1.3.1.dist-info/LICENSE.txt
ambiance-1.3.1.dist-info/METADATA
ambiance-1.3.1.dist-info/WHEEL
ambiance-1.3.1.dist-info/top_level.txt
ambiance-1.3.1.dist-info/RECORD
