Metadata-Version: 2.1
Name: ambiance
Version: 1.3.1
Summary: A full implementation of the ICAO standard atmosphere 1993
Home-page: https://github.com/airinnova/ambiance/
Author: Aaron Dettmann
Author-email: dettmann@kth.se
License: Apache License 2.0
Project-URL: Documentation, https://ambiance.readthedocs.io/
Project-URL: Source, https://github.com/airinnova/ambiance/
Project-URL: Tracker, https://github.com/airinnova/ambiance/issues
Platform: UNKNOWN
Classifier: Programming Language :: Python :: 3
Classifier: Programming Language :: Python :: 3.6
Classifier: License :: OSI Approved :: Apache Software License
Classifier: Operating System :: OS Independent
Classifier: Environment :: Console
Classifier: Intended Audience :: Developers
Classifier: Intended Audience :: Education
Classifier: Intended Audience :: Science/Research
Classifier: Topic :: Scientific/Engineering
Classifier: Topic :: Scientific/Engineering :: Physics
Classifier: Topic :: Scientific/Engineering :: Atmospheric Science
Requires-Python: >=3.6.0
License-File: LICENSE.txt
Requires-Dist: numpy
Requires-Dist: scipy
